{"cameraMode":{"drawMode":0,"name":"Shaded","section":"Shading Mode"},"sceneLighting":false,"audioPlay":false,"sceneViewState":{"m_AlwaysRefresh":false,"showFog":true,"showSkybox":false,"showFlares":true,"showImageEffects":true,"showParticleSystems":true,"showVisualEffectGraphs":true,"m_FxEnabled":true},"in2DMode":false,"pivot":{"x":-0.0025829076766967775,"y":0.0,"z":-0.03974878787994385},"rotation":{"x":0.26085346937179568,"y":0.22395533323287965,"z":-0.06234314292669296,"w":0.9370699524879456},"size":5.56620979309082,"orthographic":false}